balderhub/rfb/__init__.py
balderhub/rfb/_version.py
balderhub/rfb/lib/__init__.py
balderhub/rfb/lib/connections.py
balderhub/rfb/lib/exceptions.py
balderhub/rfb/lib/features/__init__.py
balderhub/rfb/lib/features/client/__init__.py
balderhub/rfb/lib/features/client/error_message_viewer_feature.py
balderhub/rfb/lib/features/client/rfb_client_error_message_config.py
balderhub/rfb/lib/features/client/rfb_client_feature.py
balderhub/rfb/lib/features/server/__init__.py
balderhub/rfb/lib/features/server/closed_port_config.py
balderhub/rfb/lib/features/server/password_setter_feature.py
balderhub/rfb/lib/features/server/protocol_injector_feature.py
balderhub/rfb/lib/features/server/rfb_server_config.py
balderhub/rfb/lib/features/server/rfb_server_feature.py
balderhub/rfb/lib/features/server/sec_result_injector_feature.py
balderhub/rfb/lib/features/server/security_type_injector_feature.py
balderhub/rfb/lib/setup_features/__init__.py
balderhub/rfb/lib/setup_features/client/__init__.py
balderhub/rfb/lib/setup_features/server/__init__.py
balderhub/rfb/lib/setup_features/server/local_test_rfb_server_feature.py
balderhub/rfb/lib/setup_features/server/password_setter_feature.py
balderhub/rfb/lib/setup_features/server/protocol_injector_feature.py
balderhub/rfb/lib/setup_features/server/sec_result_injector_feature.py
balderhub/rfb/lib/setup_features/server/security_type_injector_feature.py
balderhub/rfb/lib/utils/__init__.py
balderhub/rfb/lib/utils/rfb_server.py
balderhub/rfb/lib/utils/tcp_server.py
balderhub/rfb/scenarios/__init__.py
balderhub/rfb/scenarios/client/__init__.py
balderhub/rfb/scenarios/client/client2server/__init__.py
balderhub/rfb/scenarios/client/client2server/client_cut_text/__init__.py
balderhub/rfb/scenarios/client/client2server/framebuffer_update_request/__init__.py
balderhub/rfb/scenarios/client/client2server/key_event/__init__.py
balderhub/rfb/scenarios/client/client2server/pointer_event/__init__.py
balderhub_rfb-0.0.1b0.dist-info/LICENSE
balderhub_rfb-0.0.1b0.dist-info/METADATA
balderhub_rfb-0.0.1b0.dist-info/WHEEL
balderhub_rfb-0.0.1b0.dist-info/top_level.txt
balderhub_rfb-0.0.1b0.dist-info/RECORD
